{"imagePath":"texture.png","name":"ship1","SubTexture":[{"width":146,"y":200,"height":9,"name":"effect_suiwei1","x":1},{"width":180,"y":1,"height":51,"name":"chuan_1","x":1},{"width":182,"y":104,"height":23,"name":"effect_zongsuihua1","x":1},{"width":146,"y":222,"height":9,"name":"effect_suiwei3","x":1},{"width":146,"y":189,"height":9,"name":"effect_suiwei2","x":1},{"width":182,"y":54,"height":23,"name":"effect_zongsuihua2","x":1},{"width":146,"y":178,"height":9,"name":"effect_suiwei5","x":1},{"width":182,"y":79,"height":23,"name":"effect_zongsuihua3","x":1},{"y":154,"frameX":0,"frameHeight":23,"frameY":-1,"width":181,"frameWidth":182,"height":22,"name":"effect_zongsuihua4","x":1},{"y":129,"frameX":0,"frameHeight":23,"frameY":0,"width":181,"frameWidth":182,"height":23,"name":"effect_zongsuihua5","x":1},{"width":146,"y":211,"height":9,"name":"effect_suiwei4","x":1}]}